Wappalyzer/Wappalyzer.py
Wappalyzer/WebPage.py
Wappalyzer/__init__.py
Wappalyzer/data/apps.json
python3_Wappalyzer-0.1.22.dist-info/LICENSE
python3_Wappalyzer-0.1.22.dist-info/METADATA
python3_Wappalyzer-0.1.22.dist-info/WHEEL
python3_Wappalyzer-0.1.22.dist-info/top_level.txt
python3_Wappalyzer-0.1.22.dist-info/RECORD
