Metadata-Version: 2.1
Name: python3-Wappalyzer
Version: 0.1.22
Summary: Python3 driver for Wappalyzer, a web application detection utility.
Home-page: https://github.com/datasploit3/python3-Wappalyzer
Author: @datasploit
License: UNKNOWN
Platform: UNKNOWN
Classifier: Programming Language :: Python :: 3
Classifier: License :: OSI Approved :: GNU General Public License v3 (GPLv3)
Classifier: Operating System :: OS Independent
Requires-Dist: BeautifulSoup4
Requires-Dist: requests
